{
  "updated": "2026-02-25T03:35:02.631Z",
  "totalPositions": 140,
  "openPositions": 2,
  "closedPositions": 138,
  "trades": [
    {
      "token": "LOOK",
      "pnl": -4.5,
      "reason": "Volume dried up",
      "time": "2026-02-25 01:52:47",
      "exitType": "exit"
    },
    {
      "token": "Pippkin",
      "pnl": 9.5,
      "reason": "Timeout: 46min, only +9.5%",
      "time": "2026-02-25 02:03:33",
      "exitType": "timeout"
    },
    {
      "token": "Buttcoin",
      "pnl": -6.2,
      "reason": "Volume dried up",
      "time": "2026-02-25 02:07:19",
      "exitType": "exit"
    },
    {
      "token": "Djungelskog:",
      "pnl": -20,
      "reason": "stop_loss",
      "time": "2026-02-25 02:12:58",
      "exitType": "stop"
    },
    {
      "token": "triggered",
      "pnl": -20,
      "reason": "stop_loss",
      "time": "2026-02-25 02:13:03",
      "exitType": "stop"
    },
    {
      "token": "TETSUO",
      "pnl": -1.8,
      "reason": "Volume dried up",
      "time": "2026-02-25 02:25:03",
      "exitType": "exit"
    },
    {
      "token": "Kurumi",
      "pnl": -3,
      "reason": "Volume dried up",
      "time": "2026-02-25 02:47:03",
      "exitType": "exit"
    },
    {
      "token": "KIMCHI",
      "pnl": -3.3,
      "reason": "Volume dried up",
      "time": "2026-02-25 03:05:18",
      "exitType": "exit"
    }
  ],
  "tradeCount": 8,
  "winRate": "13",
  "wins": 1,
  "losses": 7,
  "avgWin": "9.5",
  "avgLoss": "-8.4",
  "bestTrade": {
    "token": "Pippkin",
    "pnl": 9.5,
    "reason": "Timeout: 46min, only +9.5%",
    "time": "2026-02-25 02:03:33",
    "exitType": "timeout"
  },
  "worstTrade": {
    "token": "Djungelskog:",
    "pnl": -20,
    "reason": "stop_loss",
    "time": "2026-02-25 02:12:58",
    "exitType": "stop"
  },
  "decisions": [
    {
      "token": "WANKEY",
      "approved": false,
      "confidence": 0,
      "reasoning": ""
    },
    {
      "token": "$WIF",
      "approved": false,
      "confidence": 0,
      "reasoning": ""
    },
    {
      "token": "DATBOI",
      "approved": true,
      "confidence": 0,
      "reasoning": ""
    },
    {
      "token": "KLED",
      "approved": false,
      "confidence": 0,
      "reasoning": ""
    },
    {
      "token": "Minna",
      "approved": false,
      "confidence": 0,
      "reasoning": ""
    },
    {
      "token": "UFO",
      "approved": true,
      "confidence": 0,
      "reasoning": ""
    },
    {
      "token": "GME",
      "approved": false,
      "confidence": 0,
      "reasoning": ""
    },
    {
      "token": "GOON",
      "approved": false,
      "confidence": 0,
      "reasoning": ""
    },
    {
      "token": "APES",
      "approved": false,
      "confidence": 0,
      "reasoning": ""
    },
    {
      "token": "LFGO",
      "approved": true,
      "confidence": 0,
      "reasoning": ""
    }
  ],
  "openList": [
    {
      "token": "UFO",
      "strategy": "paper_dca_paper_cluster"
    },
    {
      "token": "LFGO",
      "strategy": "paper_cluster"
    }
  ]
}