{
  "updated": "2026-02-24T20:20:03.130Z",
  "totalPositions": 44,
  "openPositions": 4,
  "closedPositions": 40,
  "trades": [],
  "tradeCount": 0,
  "winRate": "0",
  "wins": 0,
  "losses": 0,
  "avgWin": "0",
  "avgLoss": "0",
  "bestTrade": null,
  "worstTrade": null,
  "decisions": [],
  "openList": [
    {
      "token": "REVAunits",
      "strategy": "paper_momentum"
    },
    {
      "token": "BLOODNUT",
      "strategy": "paper_momentum"
    },
    {
      "token": "DARWIN",
      "strategy": "paper_momentum"
    },
    {
      "token": "CLAW",
      "strategy": "paper_momentum"
    }
  ]
}